{"3": {"polynomial_w_coef": {"M": {"a": {"1. Accuracy": 0.8678678678678678, "2. High confidence (0.8 quantile) accuracy": null, "3. Average confidence (0.5 quantile) accuracy": null, "4. Above worst confidence (0.2 quantile) accuracy": null, "5. Subset acc/conf": null, "6. Full dataset acc/conf": null, "7. Confidence weighted accuracy": 0.8678678678678678, "8. Training time": 22.28026008605957, "9. Nr Epochs": 620}, "b": {"1. Accuracy": 0.9579579579579579, "2. High confidence (0.8 quantile) accuracy": null, "3. Average confidence (0.5 quantile) accuracy": null, "4. Above worst confidence (0.2 quantile) accuracy": null, "5. Subset acc/conf": null, "6. Full dataset acc/conf": null, "7. Confidence weighted accuracy": 0.9579579579579579, "8. Training time": 90.24129128456116, "9. Nr Epochs": 2530}, "c": {"1. Accuracy": -0.08708708708708708, "2. High confidence (0.8 quantile) accuracy": null, "3. Average confidence (0.5 quantile) accuracy": null, "4. Above worst confidence (0.2 quantile) accuracy": null, "5. Subset acc/conf": null, "6. Full dataset acc/conf": null, "7. Confidence weighted accuracy": -0.08708708708708708, "8. Training time": 3.55824613571167, "9. Nr Epochs": 100}}, "M+C": {"a": {"1. Accuracy": 0.8558558558558559, "2. High confidence (0.8 quantile) accuracy": 1.0, "3. Average confidence (0.5 quantile) accuracy": 1.0, "4. Above worst confidence (0.2 quantile) accuracy": 0.8558558558558559, "5. Subset acc/conf": 0.9655211980347668, "6. Full dataset acc/conf": 0.9700305512186529, "7. Confidence weighted accuracy": 0.832668263632972, "8. Training time": 33.02453875541687, "9. Nr Epochs": 537}, "b": {"1. Accuracy": 0.93993993993994, "2. High confidence (0.8 quantile) accuracy": 1.0, "3. Average confidence (0.5 quantile) accuracy": 1.0, "4. Above worst confidence (0.2 quantile) accuracy": 0.93993993993994, "5. Subset acc/conf": 0.9944811926142298, "6. Full dataset acc/conf": 0.9995682058312275, "7. Confidence weighted accuracy": 0.9223953233108865, "8. Training time": 186.41350078582764, "9. Nr Epochs": 3000}, "c": {"1. Accuracy": -0.08108108108108109, "2. High confidence (0.8 quantile) accuracy": 0.582089552238806, "3. Average confidence (0.5 quantile) accuracy": 0.21686746987951808, "4. Above worst confidence (0.2 quantile) accuracy": 0.5681818181818182, "5. Subset acc/conf": 1.0198204007053513, "6. Full dataset acc/conf": 1.1127231662192452, "7. Confidence weighted accuracy": 0.04611760189941338, "8. Training time": 8.370070457458496, "9. Nr Epochs": 129}}, "MC": {"a": {"1. Accuracy": 0.8858858858858859, "2. High confidence (0.8 quantile) accuracy": 1.0, "3. Average confidence (0.5 quantile) accuracy": 1.0, "4. Above worst confidence (0.2 quantile) accuracy": 0.8858858858858859, "5. Subset acc/conf": 0.9905653147732042, "6. Full dataset acc/conf": 0.9829804142718052, "7. Confidence weighted accuracy": 0.8576615146688513, "8. Training time": 56.95647358894348, "9. Nr Epochs": 743}, "b": {"1. Accuracy": 0.7177177177177178, "2. High confidence (0.8 quantile) accuracy": 0.9701492537313433, "3. Average confidence (0.5 quantile) accuracy": 0.927710843373494, "4. Above worst confidence (0.2 quantile) accuracy": 0.7177177177177178, "5. Subset acc/conf": 0.9898687334406951, "6. Full dataset acc/conf": 0.9812416421658391, "7. Confidence weighted accuracy": 0.6593619352346426, "8. Training time": 218.7747082710266, "9. Nr Epochs": 3000}, "c": {"1. Accuracy": -0.08708708708708708, "2. High confidence (0.8 quantile) accuracy": -0.40298507462686567, "3. Average confidence (0.5 quantile) accuracy": -0.24096385542168675, "4. Above worst confidence (0.2 quantile) accuracy": NaN, "5. Subset acc/conf": 2.094379891865002, "6. Full dataset acc/conf": 2.462539897149747, "7. Confidence weighted accuracy": -0.03614398765492367, "8. Training time": 10.348938703536987, "9. Nr Epochs": 124}}, "Mprim": {"a": {"1. Accuracy": 0.9039039039039038, "2. High confidence (0.8 quantile) accuracy": 0.9701492537313433, "3. Average confidence (0.5 quantile) accuracy": 0.9759036144578314, "4. Above worst confidence (0.2 quantile) accuracy": 0.9039039039039038, "5. Subset acc/conf": 0.9596606331665937, "6. Full dataset acc/conf": 0.957877989780357, "7. Confidence weighted accuracy": 0.9021721292544413, "8. Training time": 182.787921667099, "9. Nr Epochs": 3000}, "b": {"1. Accuracy": 0.987987987987988, "2. High confidence (0.8 quantile) accuracy": 0.9701492537313433, "3. Average confidence (0.5 quantile) accuracy": 0.9879518072289156, "4. Above worst confidence (0.2 quantile) accuracy": 0.987987987987988, "5. Subset acc/conf": 1.004230832818283, "6. Full dataset acc/conf": 0.9983285836111291, "7. Confidence weighted accuracy": 0.9837515670973975, "8. Training time": 179.0905921459198, "9. Nr Epochs": 3000}, "c": {"1. Accuracy": -0.09309309309309309, "2. High confidence (0.8 quantile) accuracy": -0.4626865671641791, "3. Average confidence (0.5 quantile) accuracy": -0.3253012048192771, "4. Above worst confidence (0.2 quantile) accuracy": NaN, "5. Subset acc/conf": 3.777526344265721, "6. Full dataset acc/conf": 3.968490812446131, "7. Confidence weighted accuracy": -0.014577855107125576, "8. Training time": 5.222885847091675, "9. Nr Epochs": 83}}}, "linear": {"M": {"a": {"1. Accuracy": 0.9579579579579579, "2. High confidence (0.8 quantile) accuracy": null, "3. Average confidence (0.5 quantile) accuracy": null, "4. Above worst confidence (0.2 quantile) accuracy": null, "5. Subset acc/conf": null, "6. Full dataset acc/conf": null, "7. Confidence weighted accuracy": 0.9579579579579579, "8. Training time": 18.307692766189575, "9. Nr Epochs": 516}, "b": {"1. Accuracy": 0.963963963963964, "2. High confidence (0.8 quantile) accuracy": null, "3. Average confidence (0.5 quantile) accuracy": null, "4. Above worst confidence (0.2 quantile) accuracy": null, "5. Subset acc/conf": null, "6. Full dataset acc/conf": null, "7. Confidence weighted accuracy": 0.963963963963964, "8. Training time": 105.50611996650696, "9. Nr Epochs": 3000}, "c": {"1. Accuracy": 0.7597597597597597, "2. High confidence (0.8 quantile) accuracy": null, "3. Average confidence (0.5 quantile) accuracy": null, "4. Above worst confidence (0.2 quantile) accuracy": null, "5. Subset acc/conf": null, "6. Full dataset acc/conf": null, "7. Confidence weighted accuracy": 0.7597597597597597, "8. Training time": 66.92695546150208, "9. Nr Epochs": 1887}}, "M+C": {"a": {"1. Accuracy": 0.963963963963964, "2. High confidence (0.8 quantile) accuracy": 1.0, "3. Average confidence (0.5 quantile) accuracy": 1.0, "4. Above worst confidence (0.2 quantile) accuracy": 0.963963963963964, "5. Subset acc/conf": 1.0147378855380653, "6. Full dataset acc/conf": 1.0250833536518895, "7. Confidence weighted accuracy": 0.9249376130175662, "8. Training time": 108.17571592330933, "9. Nr Epochs": 1784}, "b": {"1. Accuracy": 0.9579579579579579, "2. High confidence (0.8 quantile) accuracy": 0.9402985074626866, "3. Average confidence (0.5 quantile) accuracy": 0.9397590361445783, "4. Above worst confidence (0.2 quantile) accuracy": 0.9579579579579579, "5. Subset acc/conf": 1.0883824007479557, "6. Full dataset acc/conf": 1.0961947653354647, "7. Confidence weighted accuracy": 0.8533567372743074, "8. Training time": 160.73716354370117, "9. Nr Epochs": 2617}, "c": {"1. Accuracy": 0.7957957957957958, "2. High confidence (0.8 quantile) accuracy": 1.0, "3. Average confidence (0.5 quantile) accuracy": 1.0, "4. Above worst confidence (0.2 quantile) accuracy": 0.7957957957957958, "5. Subset acc/conf": 1.0583458352638415, "6. Full dataset acc/conf": 1.1128770384864854, "7. Confidence weighted accuracy": 0.664091789865637, "8. Training time": 178.60347962379456, "9. Nr Epochs": 2908}}, "MC": {"a": {"1. Accuracy": 0.9519519519519519, "2. High confidence (0.8 quantile) accuracy": 1.0, "3. Average confidence (0.5 quantile) accuracy": 1.0, "4. Above worst confidence (0.2 quantile) accuracy": 0.9519519519519519, "5. Subset acc/conf": 1.0246060777251336, "6. Full dataset acc/conf": 1.0483940977772224, "7. Confidence weighted accuracy": 0.8900207590770435, "8. Training time": 98.62889194488525, "9. Nr Epochs": 1364}, "b": {"1. Accuracy": 0.7957957957957958, "2. High confidence (0.8 quantile) accuracy": 1.0, "3. Average confidence (0.5 quantile) accuracy": 0.9879518072289156, "4. Above worst confidence (0.2 quantile) accuracy": 0.7957957957957958, "5. Subset acc/conf": 1.071153724406252, "6. Full dataset acc/conf": 1.015257924584642, "7. Confidence weighted accuracy": 0.7284127191022352, "8. Training time": 56.594441175460815, "9. Nr Epochs": 802}, "c": {"1. Accuracy": 0.8378378378378378, "2. High confidence (0.8 quantile) accuracy": 0.9402985074626866, "3. Average confidence (0.5 quantile) accuracy": 0.963855421686747, "4. Above worst confidence (0.2 quantile) accuracy": 0.8466257668711656, "5. Subset acc/conf": 1.0927335975665107, "6. Full dataset acc/conf": 1.017960565896755, "7. Confidence weighted accuracy": 0.7763566287072213, "8. Training time": 200.28255796432495, "9. Nr Epochs": 2778}}, "Mprim": {"a": {"1. Accuracy": 0.9459459459459459, "2. High confidence (0.8 quantile) accuracy": 1.0, "3. Average confidence (0.5 quantile) accuracy": 0.9879518072289156, "4. Above worst confidence (0.2 quantile) accuracy": 0.9459459459459459, "5. Subset acc/conf": 1.0021121237817778, "6. Full dataset acc/conf": 1.0414069794644532, "7. Confidence weighted accuracy": 0.8868797969173741, "8. Training time": 17.83577823638916, "9. Nr Epochs": 296}, "b": {"1. Accuracy": 0.7957957957957958, "2. High confidence (0.8 quantile) accuracy": 0.9402985074626866, "3. Average confidence (0.5 quantile) accuracy": 0.9518072289156626, "4. Above worst confidence (0.2 quantile) accuracy": 0.7957957957957958, "5. Subset acc/conf": 1.0250815136013693, "6. Full dataset acc/conf": 1.0149773381984477, "7. Confidence weighted accuracy": 0.7277500702812149, "8. Training time": 27.902559518814087, "9. Nr Epochs": 463}, "c": {"1. Accuracy": 0.7357357357357357, "2. High confidence (0.8 quantile) accuracy": 1.0, "3. Average confidence (0.5 quantile) accuracy": 1.0, "4. Above worst confidence (0.2 quantile) accuracy": 0.7431192660550459, "5. Subset acc/conf": 1.0544702994990678, "6. Full dataset acc/conf": 1.062173295089604, "7. Confidence weighted accuracy": 0.653923128728752, "8. Training time": 51.690606355667114, "9. Nr Epochs": 855}}}, "polynomial": {"M": {"a": {"1. Accuracy": 0.9279279279279279, "2. High confidence (0.8 quantile) accuracy": null, "3. Average confidence (0.5 quantile) accuracy": null, "4. Above worst confidence (0.2 quantile) accuracy": null, "5. Subset acc/conf": null, "6. Full dataset acc/conf": null, "7. Confidence weighted accuracy": 0.9279279279279279, "8. Training time": 105.71784806251526, "9. Nr Epochs": 3000}, "b": {"1. Accuracy": 0.7237237237237237, "2. High confidence (0.8 quantile) accuracy": null, "3. Average confidence (0.5 quantile) accuracy": null, "4. Above worst confidence (0.2 quantile) accuracy": null, "5. Subset acc/conf": null, "6. Full dataset acc/conf": null, "7. Confidence weighted accuracy": 0.7237237237237237, "8. Training time": 106.73303937911987, "9. Nr Epochs": 3000}, "c": {"1. Accuracy": -0.12312312312312312, "2. High confidence (0.8 quantile) accuracy": null, "3. Average confidence (0.5 quantile) accuracy": null, "4. Above worst confidence (0.2 quantile) accuracy": null, "5. Subset acc/conf": null, "6. Full dataset acc/conf": null, "7. Confidence weighted accuracy": -0.12312312312312312, "8. Training time": 3.0708112716674805, "9. Nr Epochs": 88}}, "M+C": {"a": {"1. Accuracy": 0.9519519519519519, "2. High confidence (0.8 quantile) accuracy": 1.0, "3. Average confidence (0.5 quantile) accuracy": 0.9879518072289156, "4. Above worst confidence (0.2 quantile) accuracy": 0.9519519519519519, "5. Subset acc/conf": 0.9880492525710054, "6. Full dataset acc/conf": 0.9915363518314374, "7. Confidence weighted accuracy": 0.9409160665921621, "8. Training time": 184.28949403762817, "9. Nr Epochs": 3000}, "b": {"1. Accuracy": 0.9219219219219219, "2. High confidence (0.8 quantile) accuracy": 1.0, "3. Average confidence (0.5 quantile) accuracy": 0.9879518072289156, "4. Above worst confidence (0.2 quantile) accuracy": 0.9219219219219219, "5. Subset acc/conf": 0.9489683476327689, "6. Full dataset acc/conf": 0.9641979119368937, "7. Confidence weighted accuracy": 0.9258781556968574, "8. Training time": 184.8257293701172, "9. Nr Epochs": 3000}, "c": {"1. Accuracy": 0.7357357357357357, "2. High confidence (0.8 quantile) accuracy": 1.0, "3. Average confidence (0.5 quantile) accuracy": 0.9759036144578314, "4. Above worst confidence (0.2 quantile) accuracy": 0.7357357357357357, "5. Subset acc/conf": 0.9644414582594721, "6. Full dataset acc/conf": 0.9567390734022126, "7. Confidence weighted accuracy": 0.7255137501894174, "8. Training time": 182.2259407043457, "9. Nr Epochs": 3000}}, "MC": {"a": {"1. Accuracy": 0.933933933933934, "2. High confidence (0.8 quantile) accuracy": 1.0, "3. Average confidence (0.5 quantile) accuracy": 1.0, "4. Above worst confidence (0.2 quantile) accuracy": 0.933933933933934, "5. Subset acc/conf": 0.980572953566503, "6. Full dataset acc/conf": 0.9472929693664734, "7. Confidence weighted accuracy": 0.9602254863615867, "8. Training time": 107.5919189453125, "9. Nr Epochs": 1511}, "b": {"1. Accuracy": 0.7057057057057057, "2. High confidence (0.8 quantile) accuracy": 0.9701492537313433, "3. Average confidence (0.5 quantile) accuracy": 0.927710843373494, "4. Above worst confidence (0.2 quantile) accuracy": 0.7057057057057057, "5. Subset acc/conf": 0.9084293060681288, "6. Full dataset acc/conf": 0.9604645781872441, "7. Confidence weighted accuracy": 0.6487160357269081, "8. Training time": 212.39381957054138, "9. Nr Epochs": 3000}, "c": {"1. Accuracy": 0.6936936936936937, "2. High confidence (0.8 quantile) accuracy": 0.9104477611940298, "3. Average confidence (0.5 quantile) accuracy": 0.9397590361445783, "4. Above worst confidence (0.2 quantile) accuracy": 0.6927710843373494, "5. Subset acc/conf": 0.9508685252893153, "6. Full dataset acc/conf": 0.9831297602291955, "7. Confidence weighted accuracy": 0.6290622417991226, "8. Training time": 215.5392200946808, "9. Nr Epochs": 3000}}, "Mprim": {"a": {"1. Accuracy": 0.06306306306306306, "2. High confidence (0.8 quantile) accuracy": -0.582089552238806, "3. Average confidence (0.5 quantile) accuracy": -0.2891566265060241, "4. Above worst confidence (0.2 quantile) accuracy": NaN, "5. Subset acc/conf": 6.904527334641628, "6. Full dataset acc/conf": 6.604313559418384, "7. Confidence weighted accuracy": -0.002609802001678908, "8. Training time": 1.2076811790466309, "9. Nr Epochs": 18}, "b": {"1. Accuracy": 0.9039039039039038, "2. High confidence (0.8 quantile) accuracy": 0.9701492537313433, "3. Average confidence (0.5 quantile) accuracy": 0.963855421686747, "4. Above worst confidence (0.2 quantile) accuracy": 0.9039039039039038, "5. Subset acc/conf": 0.9533686831946854, "6. Full dataset acc/conf": 0.9696523399710223, "7. Confidence weighted accuracy": 0.8946329537812654, "8. Training time": 147.85854125022888, "9. Nr Epochs": 2370}, "c": {"1. Accuracy": 0.6756756756756757, "2. High confidence (0.8 quantile) accuracy": 1.0, "3. Average confidence (0.5 quantile) accuracy": 0.9397590361445783, "4. Above worst confidence (0.2 quantile) accuracy": 0.6756756756756757, "5. Subset acc/conf": 0.8053570442280795, "6. Full dataset acc/conf": 0.8671750535816989, "7. Confidence weighted accuracy": 0.6983829285647418, "8. Training time": 192.443665266037, "9. Nr Epochs": 3000}}}}}